neurohub/__init__.py
neurohub/base.py
neurohub/checklists.py
neurohub/clients.py
neurohub/criteria.py
neurohub/criteria_groups.py
neurohub/criteria_result.py
neurohub/departments.py
neurohub/errors.py
neurohub/file.py
neurohub/managers.py
neurohub/root.py
neurohub/transcriptions.py
neurohub/types.py
neurohub-0.0.7.dist-info/licenses/LICENSE
neurohub-0.0.7.dist-info/METADATA
neurohub-0.0.7.dist-info/WHEEL
neurohub-0.0.7.dist-info/top_level.txt
neurohub-0.0.7.dist-info/RECORD
