Metadata-Version: 2.4
Name: neurohub
Version: 0.0.7
Summary: A python wrapper for neurohub API
Author-email: Kamatayon <wowegable@gmail.com>
License-Expression: MIT
Project-URL: Homepage, https://github.com/Kamatayon/neurohub
Project-URL: Issues, https://github.com/Kamatayon/neurohub
Classifier: Programming Language :: Python :: 3
Classifier: Operating System :: OS Independent
Requires-Python: >=3.9
License-File: LICENSE
Requires-Dist: httpx
Dynamic: license-file
